springstream/__init__.py
springstream/common.py
springstream/springstream.py
springstream-0.0.1.dist-info/LICENSE
springstream-0.0.1.dist-info/METADATA
springstream-0.0.1.dist-info/WHEEL
springstream-0.0.1.dist-info/entry_points.txt
springstream-0.0.1.dist-info/top_level.txt
springstream-0.0.1.dist-info/RECORD
